wizata_test_lib/__init__.py
wizata_test_lib/samples.py
wizata_test_lib-0.1.dist-info/METADATA
wizata_test_lib-0.1.dist-info/WHEEL
wizata_test_lib-0.1.dist-info/top_level.txt
wizata_test_lib-0.1.dist-info/RECORD
