Metadata-Version: 2.1
Name: wizata-test-lib
Version: 0.1
Summary: Wizata Sample Library
Author: Wizata S.A.
Author-email: info@wizata.com
